odoo/addons/mail_activity_done/LICENSE
odoo/addons/mail_activity_done/README.rst
odoo/addons/mail_activity_done/__init__.py
odoo/addons/mail_activity_done/__manifest__.py
odoo/addons/mail_activity_done/hooks.py
odoo/addons/mail_activity_done/i18n/de.po
odoo/addons/mail_activity_done/i18n/mail_activity_done.pot
odoo/addons/mail_activity_done/models/__init__.py
odoo/addons/mail_activity_done/models/mail_activity.py
odoo/addons/mail_activity_done/models/res_users.py
odoo/addons/mail_activity_done/readme/CONTRIBUTORS.rst
odoo/addons/mail_activity_done/readme/DESCRIPTION.rst
odoo/addons/mail_activity_done/static/description/icon.png
odoo/addons/mail_activity_done/static/description/index.html
odoo/addons/mail_activity_done/static/src/js/mail_activity.js
odoo/addons/mail_activity_done/tests/__init__.py
odoo/addons/mail_activity_done/tests/test_mail_activity_done.py
odoo/addons/mail_activity_done/views/mail_activity_views.xml
odoo/addons/mail_activity_done/views/templates.xml
odoo11_addon_mail_activity_done-11.0.1.1.0.dist-info/METADATA
odoo11_addon_mail_activity_done-11.0.1.1.0.dist-info/RECORD
odoo11_addon_mail_activity_done-11.0.1.1.0.dist-info/WHEEL
odoo11_addon_mail_activity_done-11.0.1.1.0.dist-info/top_level.txt
